{
    "results": {
        "biology-zoological-557b476d452d1.pdf": {
            "title": 100,
            "authors": 0,
            "emails": 0,
            "abstract": 99.59,
            "references": 13.06
        },
        "biology-zoological-557b476d453a6.pdf": {
            "title": 100,
            "authors": 30.23,
            "emails": 100,
            "abstract": 99.44,
            "references": 100
        },
        "biology-zoological-557b476d453f9.pdf": {
            "title": 100,
            "authors": 100,
            "emails": 100,
            "abstract": 98.1,
            "references": 93.55
        },
        "biology-zoological-557b476d4533a.pdf": {
            "title": 100,
            "authors": 100,
            "emails": 0,
            "abstract": 0,
            "references": 97.6
        },
        "biology-zoological-557b476d4544c.pdf": {
            "title": 100,
            "authors": 81.91,
            "emails": 100,
            "abstract": 96.88,
            "references": 100
        },
        "biology-zoological-557b476d45277.pdf": {
            "title": 98.43,
            "authors": 100,
            "emails": 0,
            "abstract": 100,
            "references": 78.44
        },
        "biology-zoological-558720773456f.pdf": {
            "title": 100,
            "authors": 100,
            "emails": 0,
            "abstract": 99.19,
            "references": 23.33
        }
    }
}